diive/__init__.py
diive/configs/exampledata/__init__.py
diive/configs/exampledata/EDDYPRO-FLUXNET-CSV-30MIN_multiple/eddypro_CH-HON_FR-20240818-090003_fluxnet_2024-08-18T090018_adv.csv
diive/configs/exampledata/EDDYPRO-FLUXNET-CSV-30MIN_multiple/eddypro_CH-HON_FR-20240819-090003_fluxnet_2024-08-19T090019_adv.csv
diive/configs/exampledata/EDDYPRO-FLUXNET-CSV-30MIN_multiple/eddypro_CH-HON_FR-20240820-090004_fluxnet_2024-08-20T090021_adv.csv
diive/configs/exampledata/exampledata_DIIVE-CSV-30MIN_CH-DAV_FP2022.5_2022.07_ID20230206154316_30MIN.diive.csv
diive/configs/exampledata/exampledata_EDDYPRO-FLUXNET-CSV-30MIN_2012_eddypro_CH-FRU_FR-20230425-220357_fluxnet_2023-04-26T201227_adv.csv
diive/configs/exampledata/exampledata_EDDYPRO-FLUXNET-CSV-30MIN_2017_eddypro_CH-FRU_FR-20230425-205849_fluxnet_2023-04-26T204736_adv.csv
diive/configs/exampledata/exampledata_EDDYPRO-FLUXNET-CSV-30MIN_2023_eddypro_CH-FRU_FR-20240228-000000_fluxnet_MERGED_adv.csv
diive/configs/exampledata/exampledata_EDDYPRO-FLUXNET-CSV-30MIN_CH-AWS_2022.07_FR-20220127-164245_eddypro_fluxnet_2022-01-28T112538_adv.csv
diive/configs/exampledata/exampledata_EDDYPRO-FULL-OUTPUT-CSV-30MIN_eddypro_CH-FRU_FR-20240408-101506_full_output_2024-04-08T101558_adv.csv
diive/configs/exampledata/exampledata_ETH-RECORD-TOA5-CSVGZ-20HZ_CH-FRU_ec_20240404-1300.csv.gz
diive/configs/exampledata/exampledata_ETH-SONICREAD-BICO-CSVGZ-20HZ_CH-FRU_202307071300.csv.gz
diive/configs/exampledata/exampledata_FLUXNET-FULLSET-HH-CSV-30MIN_FLX_CH-Cha_FLUXNET2015_FULLSET_HH_2005-2020_beta-3.csv
diive/configs/exampledata/exampledata_GENERIC-CSV-HEADER-1ROW-TS-MIDDLE-FULL-1MIN_CH-FRU_iDL_BOX1_0_1_TBL1_20240401-0000.dat.csv
diive/configs/exampledata/exampledata_GENERIC-CSV-HEADER-1ROW-TS-MIDDLE-FULL-NS-20HZ_CH-DAS_202305130830_30MIN-SPLIT_TR.csv
diive/configs/exampledata/exampledata_GENERIC-TXT-EDDY-COVARIANCE-10Hz-2023-06-24-03-30_LGRData.txt
diive/configs/exampledata/exampledata_ICOS-H2R-CSVZIP-10S_CH-Dav_BM_20230328_L02_F03.zip
diive-0.90.0.dist-info/LICENSE
diive-0.90.0.dist-info/METADATA
diive-0.90.0.dist-info/WHEEL
diive-0.90.0.dist-info/RECORD
