Metadata-Version: 2.3
Name: diive
Version: 0.90.0
Summary: Time series processing
License: GNU General Public License v3.0
Author: Lukas Hörtnagl
Author-email: holukas@ethz.ch
Requires-Python: >=3.11,<3.12
Classifier: License :: Other/Proprietary License
Classifier: Programming Language :: Python :: 3
Classifier: Programming Language :: Python :: 3.11
Requires-Dist: bokeh (>=3.7.1,<4.0.0)
Requires-Dist: category-encoders (>=2.8.1,<3.0.0)
Requires-Dist: dtreeviz (>=2.2.2,<3.0.0)
Requires-Dist: eli5 (>=0.14.0,<0.15.0)
Requires-Dist: jupyter-bokeh (>=4.0.5,<5.0.0)
Requires-Dist: jupyterlab (>=4.3.6,<5.0.0)
Requires-Dist: matplotlib (>=3.10.1,<4.0.0)
Requires-Dist: numpy (>=2.2.4,<3.0.0)
Requires-Dist: pandas (>=2.2.3,<3.0.0)
Requires-Dist: polars (>=1.26.0,<2.0.0)
Requires-Dist: prophet (>=1.1.6,<2.0.0)
Requires-Dist: pyarrow (>=19.0.1,<20.0.0)
Requires-Dist: pymannkendall (>=1.4.3,<2.0.0)
Requires-Dist: pyyaml (>=6.0.2,<7.0.0)
Requires-Dist: scikit-learn (>=1.6.1,<2.0.0)
Requires-Dist: scikit-optimize (>=0.10.2,<0.11.0)
Requires-Dist: seaborn (>=0.13.2,<0.14.0)
Requires-Dist: shap (>=0.48.0,<0.49.0)
Requires-Dist: shapiq (>=1.3.1,<2.0.0)
Requires-Dist: sktime (>=0.36.0,<0.37.0)
Requires-Dist: statsmodels (>=0.14.4,<0.15.0)
Requires-Dist: uncertainties (>=3.2.2,<4.0.0)
Requires-Dist: xgboost (>=3.0.0,<4.0.0)
Requires-Dist: yellowbrick (>=1.5,<2.0)
